textual_imageview/__about__.py
textual_imageview/__init__.py
textual_imageview/app.py
textual_imageview/img.py
textual_imageview/viewer.py
textual_imageview-0.0.2.dist-info/METADATA
textual_imageview-0.0.2.dist-info/WHEEL
textual_imageview-0.0.2.dist-info/entry_points.txt
textual_imageview-0.0.2.dist-info/licenses/LICENSE.txt
textual_imageview-0.0.2.dist-info/RECORD
