Metadata-Version: 2.1
Name: textual-imageview
Version: 0.0.2
Summary: A simple terminal-based image viewer.
Project-URL: Documentation, https://github.com/adamviola/textual-imageview#readme
Project-URL: Issues, https://github.com/adamviola/textual-imageview/issues
Project-URL: Source, https://github.com/adamviola/textual-imageview
Author-email: Adam Viola <adam@viola.dev>
License-Expression: MIT
License-File: LICENSE.txt
Classifier: Development Status :: 4 - Beta
Classifier: Programming Language :: Python
Classifier: Programming Language :: Python :: 3.7
Classifier: Programming Language :: Python :: 3.8
Classifier: Programming Language :: Python :: 3.9
Classifier: Programming Language :: Python :: 3.10
Classifier: Programming Language :: Python :: 3.11
Classifier: Programming Language :: Python :: Implementation :: CPython
Classifier: Programming Language :: Python :: Implementation :: PyPy
Requires-Python: >=3.7
Requires-Dist: pillow>=9.4.0
Requires-Dist: rich>=13.0.0
Requires-Dist: textual>=0.9.1
